{
	"info": {
		"_postman_id": "a42fa648-faab-418c-b235-c595d9ffccb2",
		"name": "Prueba - Double Partners",
		"schema": "https://schema.getpostman.com/json/collection/v2.1.0/collection.json",
		"_exporter_id": "7570388"
	},
	"item": [
		{
			"name": "Usuario",
			"item": [
				{
					"name": "Crear usuario",
					"request": {
						"auth": {
							"type": "noauth"
						},
						"method": "POST",
						"header": [],
						"body": {
							"mode": "raw",
							"raw": "{\r\n  \"nombres\": \"Edyson\",\r\n  \"apellidos\": \"Leal\",\r\n  \"email\": \"edyson@double.com\",\r\n  \"password\": \"123456\"\r\n}",
							"options": {
								"raw": {
									"language": "json"
								}
							}
						},
						"url": {
							"raw": "{{baseUrl}}/api/v1/users/crear-usuario",
							"host": [
								"{{baseUrl}}"
							],
							"path": [
								"api",
								"v1",
								"users",
								"crear-usuario"
							]
						}
					},
					"response": []
				},
				{
					"name": "Actualizar",
					"request": {
						"auth": {
							"type": "bearer",
							"bearer": [
								{
									"key": "token",
									"value": "{{bearer}}",
									"type": "string"
								}
							]
						},
						"method": "PUT",
						"header": [],
						"body": {
							"mode": "raw",
							"raw": "{\r\n  \"nombres\": \"Edyson F.\",\r\n  \"apellidos\": \"Leal\",\r\n  \"email\": \"edyson@double.com\",\r\n  \"password\": \"123456\"\r\n}",
							"options": {
								"raw": {
									"language": "json"
								}
							}
						},
						"url": {
							"raw": "{{baseUrl}}/api/v1/users/actualizar/8138c185-14e1-4017-af2d-1848a996ca70",
							"host": [
								"{{baseUrl}}"
							],
							"path": [
								"api",
								"v1",
								"users",
								"actualizar",
								"8138c185-14e1-4017-af2d-1848a996ca70"
							]
						}
					},
					"response": []
				},
				{
					"name": "Obtener por ID",
					"request": {
						"auth": {
							"type": "bearer",
							"bearer": [
								{
									"key": "token",
									"value": "{{bearer}}",
									"type": "string"
								}
							]
						},
						"method": "GET",
						"header": [],
						"url": {
							"raw": "{{baseUrl}}/api/v1/users/obtener/8138c185-14e1-4017-af2d-1848a996ca70",
							"host": [
								"{{baseUrl}}"
							],
							"path": [
								"api",
								"v1",
								"users",
								"obtener",
								"8138c185-14e1-4017-af2d-1848a996ca70"
							]
						}
					},
					"response": []
				},
				{
					"name": "Listar usuarios",
					"request": {
						"auth": {
							"type": "bearer",
							"bearer": [
								{
									"key": "token",
									"value": "{{bearer}}",
									"type": "string"
								}
							]
						},
						"method": "GET",
						"header": [],
						"url": {
							"raw": "{{baseUrl}}/api/v1/users/listar",
							"host": [
								"{{baseUrl}}"
							],
							"path": [
								"api",
								"v1",
								"users",
								"listar"
							]
						}
					},
					"response": []
				}
			]
		},
		{
			"name": "Ticket",
			"item": [
				{
					"name": "Crear Ticket",
					"request": {
						"auth": {
							"type": "bearer",
							"bearer": [
								{
									"key": "token",
									"value": "{{bearer}}",
									"type": "string"
								}
							]
						},
						"method": "POST",
						"header": [],
						"body": {
							"mode": "raw",
							"raw": "{\r\n  \"descripcion\": \"Mi primer ticket de prueba\",\r\n  \"status\": \"ABIERTO\",\r\n  \"userId\": \"411689b0-7bd0-45a7-8e7b-cc6bf5be7a1b\"\r\n}",
							"options": {
								"raw": {
									"language": "json"
								}
							}
						},
						"url": {
							"raw": "{{baseUrl}}/api/v1/tickets/crear-ticket",
							"host": [
								"{{baseUrl}}"
							],
							"path": [
								"api",
								"v1",
								"tickets",
								"crear-ticket"
							]
						}
					},
					"response": []
				},
				{
					"name": "Actualizar",
					"request": {
						"auth": {
							"type": "bearer",
							"bearer": [
								{
									"key": "token",
									"value": "{{bearer}}",
									"type": "string"
								}
							]
						},
						"method": "PUT",
						"header": [],
						"body": {
							"mode": "raw",
							"raw": "{\r\n  \"descripcion\": \"Mi segundo ticket de prueba actualizado\",\r\n  \"status\": \"CERRADO\",\r\n  \"userId\": \"8138c185-14e1-4017-af2d-1848a996ca70\"\r\n}",
							"options": {
								"raw": {
									"language": "json"
								}
							}
						},
						"url": {
							"raw": "{{baseUrl}}/api/v1/tickets/actualizar/7460ca8f-b1bd-4175-bfba-7c004fe0fb0d",
							"host": [
								"{{baseUrl}}"
							],
							"path": [
								"api",
								"v1",
								"tickets",
								"actualizar",
								"7460ca8f-b1bd-4175-bfba-7c004fe0fb0d"
							]
						}
					},
					"response": []
				},
				{
					"name": "Eliminar",
					"request": {
						"auth": {
							"type": "bearer",
							"bearer": [
								{
									"key": "token",
									"value": "{{bearer}}",
									"type": "string"
								}
							]
						},
						"method": "DELETE",
						"header": [],
						"url": {
							"raw": "{{baseUrl}}/api/v1/tickets/eliminar/a0219d81-6a7e-4503-92a3-cf892cfc88dd",
							"host": [
								"{{baseUrl}}"
							],
							"path": [
								"api",
								"v1",
								"tickets",
								"eliminar",
								"a0219d81-6a7e-4503-92a3-cf892cfc88dd"
							]
						}
					},
					"response": []
				},
				{
					"name": "Obtener por ID",
					"request": {
						"auth": {
							"type": "bearer",
							"bearer": [
								{
									"key": "token",
									"value": "{{bearer}}",
									"type": "string"
								}
							]
						},
						"method": "GET",
						"header": [],
						"url": {
							"raw": "{{baseUrl}}/api/v1/tickets/obtener/a26d2eb5-e048-4e25-a045-8aca3be3e98b",
							"host": [
								"{{baseUrl}}"
							],
							"path": [
								"api",
								"v1",
								"tickets",
								"obtener",
								"a26d2eb5-e048-4e25-a045-8aca3be3e98b"
							]
						}
					},
					"response": []
				},
				{
					"name": "Listar tickets",
					"request": {
						"auth": {
							"type": "bearer",
							"bearer": [
								{
									"key": "token",
									"value": "{{bearer}}",
									"type": "string"
								}
							]
						},
						"method": "GET",
						"header": [],
						"url": {
							"raw": "{{baseUrl}}/api/v1/tickets/listar",
							"host": [
								"{{baseUrl}}"
							],
							"path": [
								"api",
								"v1",
								"tickets",
								"listar"
							]
						}
					},
					"response": []
				},
				{
					"name": "Filtrar",
					"request": {
						"auth": {
							"type": "bearer",
							"bearer": [
								{
									"key": "token",
									"value": "{{bearer}}",
									"type": "string"
								}
							]
						},
						"method": "POST",
						"header": [],
						"body": {
							"mode": "raw",
							"raw": "{\r\n  \"email\": \"edyson@double.com\"\r\n}",
							"options": {
								"raw": {
									"language": "json"
								}
							}
						},
						"url": {
							"raw": "{{baseUrl}}/api/v1/tickets/filter",
							"host": [
								"{{baseUrl}}"
							],
							"path": [
								"api",
								"v1",
								"tickets",
								"filter"
							]
						}
					},
					"response": []
				}
			]
		},
		{
			"name": "Login",
			"request": {
				"auth": {
					"type": "noauth"
				},
				"method": "POST",
				"header": [],
				"body": {
					"mode": "raw",
					"raw": "{\r\n    \"email\": \"edyson@double.com\",\r\n    \"password\": \"123456\"\r\n}",
					"options": {
						"raw": {
							"language": "json"
						}
					}
				},
				"url": {
					"raw": "{{baseUrl}}/api/v1/auth/login",
					"host": [
						"{{baseUrl}}"
					],
					"path": [
						"api",
						"v1",
						"auth",
						"login"
					]
				}
			},
			"response": []
		}
	],
	"event": [
		{
			"listen": "prerequest",
			"script": {
				"type": "text/javascript",
				"packages": {},
				"requests": {},
				"exec": [
					""
				]
			}
		},
		{
			"listen": "test",
			"script": {
				"type": "text/javascript",
				"packages": {},
				"requests": {},
				"exec": [
					""
				]
			}
		}
	],
	"variable": [
		{
			"key": "baseUrl",
			"value": ""
		},
		{
			"key": "bearer",
			"value": ""
		}
	]
}